manim_graphing/__init__.py
manim_graphing/__main__.py
manim_graphing/graphs/PieChart.py
manim_graphing-0.1.0.dist-info/entry_points.txt
manim_graphing-0.1.0.dist-info/LICENSE
manim_graphing-0.1.0.dist-info/WHEEL
manim_graphing-0.1.0.dist-info/METADATA
manim_graphing-0.1.0.dist-info/RECORD
