Metadata-Version: 2.1
Name: manim-graphing
Version: 0.1.0
Summary: A Manim Plugin for Graphing
Home-page: https://github.com/GameDungeon/manim-graphing
Author: GameDungeon
Author-email: gamedungeon@protonmail.com
Requires-Python: >=3.8,<4.0
Classifier: Programming Language :: Python :: 3
Classifier: Programming Language :: Python :: 3.8
Classifier: Programming Language :: Python :: 3.9
Requires-Dist: manim (>=0.3.0)
Project-URL: Repository, https://github.com/GameDungeon/manim-graphing
